odoo/addons/fleet_vehicle_fuel_capacity/README.rst
odoo/addons/fleet_vehicle_fuel_capacity/__init__.py
odoo/addons/fleet_vehicle_fuel_capacity/__manifest__.py
odoo/addons/fleet_vehicle_fuel_capacity/i18n/es.po
odoo/addons/fleet_vehicle_fuel_capacity/i18n/fleet_vehicle_fuel_capacity.pot
odoo/addons/fleet_vehicle_fuel_capacity/i18n/it.po
odoo/addons/fleet_vehicle_fuel_capacity/i18n/pt_BR.po
odoo/addons/fleet_vehicle_fuel_capacity/i18n/sv.po
odoo/addons/fleet_vehicle_fuel_capacity/models/__init__.py
odoo/addons/fleet_vehicle_fuel_capacity/models/fleet_vehicle.py
odoo/addons/fleet_vehicle_fuel_capacity/readme/CONTRIBUTORS.md
odoo/addons/fleet_vehicle_fuel_capacity/readme/CREDITS.md
odoo/addons/fleet_vehicle_fuel_capacity/readme/DESCRIPTION.md
odoo/addons/fleet_vehicle_fuel_capacity/readme/ROADMAP.md
odoo/addons/fleet_vehicle_fuel_capacity/static/description/banner.png
odoo/addons/fleet_vehicle_fuel_capacity/static/description/icon.png
odoo/addons/fleet_vehicle_fuel_capacity/static/description/index.html
odoo/addons/fleet_vehicle_fuel_capacity/views/fleet_vehicle.xml
odoo_addon_fleet_vehicle_fuel_capacity-18.0.1.0.0.2.dist-info/METADATA
odoo_addon_fleet_vehicle_fuel_capacity-18.0.1.0.0.2.dist-info/WHEEL
odoo_addon_fleet_vehicle_fuel_capacity-18.0.1.0.0.2.dist-info/top_level.txt
odoo_addon_fleet_vehicle_fuel_capacity-18.0.1.0.0.2.dist-info/RECORD
